voxcpmane/__init__.py
voxcpmane/server.py
voxcpmane/text_normalize.py
voxcpmane/voxcpm.py
voxcpmane/frontend/index.html
voxcpmane-0.0.4.dist-info/METADATA
voxcpmane-0.0.4.dist-info/WHEEL
voxcpmane-0.0.4.dist-info/entry_points.txt
voxcpmane-0.0.4.dist-info/top_level.txt
voxcpmane-0.0.4.dist-info/RECORD
