Metadata-Version: 2.4
Name: voxcpmane
Version: 0.0.4
Summary: VoxCPM TTS model with Apple Neural Engine backend server
Project-URL: Homepage, https://github.com/0seba/VoxCPMANE
Requires-Python: <3.13,>=3.9
Requires-Dist: coremltools==8.3.0
Requires-Dist: einops
Requires-Dist: fastapi
Requires-Dist: inflect
Requires-Dist: numpy>2
Requires-Dist: sounddevice
Requires-Dist: soundfile
Requires-Dist: soxr
Requires-Dist: transformers
Requires-Dist: uvicorn
Requires-Dist: wetext
Requires-Dist: tqdm
Requires-Dist: aiofiles
Requires-Dist: huggingface_hub
Requires-Dist: ftfy>=6.3.1
